termtitle
