Metadata-Version: 1.0
Name: termtitle
Version: 0.1.5
Summary: A command line program to change macOS terminal title
Home-page: https://github.com/grimmer0125/terminal-title-change
Author: Grimmer
Author-email: grimmer0125@gmail.com
License: MIT
Platform: UNKNOWN
